scinum/__init__.py
scinum/py.typed
scinum-2.2.2.dist-info/licenses/LICENSE
scinum-2.2.2.dist-info/METADATA
scinum-2.2.2.dist-info/WHEEL
scinum-2.2.2.dist-info/top_level.txt
scinum-2.2.2.dist-info/RECORD
