Metadata-Version: 2.4
Name: scinum
Version: 2.2.2
Summary: Scientific numbers with multiple uncertainties and correlation-aware, gaussian propagation and Numpy support.
Author-email: Marcel Rieger <marcel.rieger@cern.ch>
License: Copyright (c) 2017-2025, Marcel Rieger
Project-URL: Homepage, https://github.com/riga/scinum
Project-URL: Documentation, https://scinum.readthedocs.io
Project-URL: Repository, https://github.com/riga/scinum.git
Keywords: scientific,numbers,error,systematics,propagation
Classifier: Programming Language :: Python
Classifier: Programming Language :: Python :: 3
Classifier: Programming Language :: Python :: 3.7
Classifier: Programming Language :: Python :: 3.8
Classifier: Programming Language :: Python :: 3.9
Classifier: Programming Language :: Python :: 3.10
Classifier: Programming Language :: Python :: 3.11
Classifier: Programming Language :: Python :: 3.12
Classifier: Programming Language :: Python :: 3.13
Classifier: Development Status :: 5 - Production/Stable
Classifier: Operating System :: OS Independent
Classifier: License :: OSI Approved :: BSD License
Classifier: Intended Audience :: Developers
Classifier: Intended Audience :: Science/Research
Classifier: Intended Audience :: Information Technology
Requires-Python: >=3.7
License-File: LICENSE
Requires-Dist: typing_extensions~=4.12; python_version == "3.8"
Requires-Dist: typing_extensions~=4.7; python_version < "3.8"
Provides-Extra: dev
Requires-Dist: PyYAML; extra == "dev"
Requires-Dist: numpy<2; python_version < "3.9" and extra == "dev"
Requires-Dist: numpy; python_version >= "3.9" and extra == "dev"
Requires-Dist: uncertainties; extra == "dev"
Requires-Dist: mypy~=1.11.1; python_version >= "3.8" and extra == "dev"
Requires-Dist: flake8~=7.1.1; python_version >= "3.8" and extra == "dev"
Requires-Dist: flake8~=5.0.0; python_version < "3.8" and extra == "dev"
Requires-Dist: flake8-commas~=2.1.0; python_version < "3.8" and extra == "dev"
Requires-Dist: flake8-commas~=4.0.0; python_version >= "3.8" and extra == "dev"
Requires-Dist: flake8-quotes~=3.4.0; extra == "dev"
Requires-Dist: pytest~=7.4.4; python_version < "3.8" and extra == "dev"
Requires-Dist: pytest~=8.3.2; python_version >= "3.8" and extra == "dev"
Requires-Dist: pytest-cov~=4.1.0; python_version < "3.8" and extra == "dev"
Requires-Dist: pytest-cov~=5.0.0; python_version >= "3.8" and extra == "dev"
Requires-Dist: ipykernel~=6.29.5; python_version >= "3.8" and extra == "dev"
Requires-Dist: ipykernel~=6.16.0; python_version < "3.8" and extra == "dev"
Requires-Dist: types-docutils~=0.20.0; extra == "dev"
Provides-Extra: docs
Requires-Dist: sphinx~=8.0.2; extra == "docs"
Requires-Dist: sphinx-autodoc-typehints~=2.2.3; extra == "docs"
Requires-Dist: sphinx-book-theme~=1.1.3; extra == "docs"
Requires-Dist: sphinx-lfs-content~=1.1.7; extra == "docs"
Requires-Dist: autodocsumm~=0.2.13; extra == "docs"
Requires-Dist: myst-parser~=4.0.0; extra == "docs"
Dynamic: license-file
